odoo/addons/ssi_web_login/README.rst
odoo/addons/ssi_web_login/__init__.py
odoo/addons/ssi_web_login/__manifest__.py
odoo/addons/ssi_web_login/static/description/icon.png
odoo/addons/ssi_web_login/views/webclient_templates.xml
odoo14_addon_ssi_web_login-14.0.1.0.1.dist-info/METADATA
odoo14_addon_ssi_web_login-14.0.1.0.1.dist-info/WHEEL
odoo14_addon_ssi_web_login-14.0.1.0.1.dist-info/top_level.txt
odoo14_addon_ssi_web_login-14.0.1.0.1.dist-info/RECORD
